[
{
"srcFile" : "manifest",
"targetFile" : "00000000000000000000000000000000",
"size"       : 4677,
"version"    : 1,
"beDependent" : false,
"crc"         : 1177540667,
"resources"   : [
    "manifest"
]
},
{
"srcFile" : "scene",
"targetFile" : "264a91f6308ddca71236f3c90e63286b",
"size"       : 27967143,
"version"    : 1,
"beDependent" : false,
"crc"         : 1136807075,
"resources"   : [
    "Assets/test/yoyo(1)-10.jpg",
    "Assets/test/yoyo(1)-13.jpg",
    "Assets/test/yoyo(1)-21.jpg",
    "Assets/test/yoyo(1)-22.jpg",
    "Assets/test/yoyo(1)-23.jpg"
]
},
{
"srcFile" : "sphere",
"targetFile" : "40c8a807728c1be590f942612a6c6622",
"size"       : 2961006,
"version"    : 1,
"beDependent" : false,
"crc"         : 3671962434,
"resources"   : [
    "Assets/test/sphere.mat",
    "Assets/test/sphere.prefab"
],
"dependencies" : [
    "test-topbottom_png"
]
},
{
"srcFile" : "test",
"targetFile" : "15e4291fb32e5be05017d95d7ab2d380",
"size"       : 179653,
"version"    : 1,
"beDependent" : false,
"crc"         : 3059418318,
"resources"   : [
    "Assets/test2.unity"
]
},
{
"srcFile" : "test-cube_mat",
"targetFile" : "9596d6dbc4f8a811eabfa7f0d41164e0",
"size"       : 140802,
"version"    : 1,
"beDependent" : true,
"crc"         : 2403109339,
"resources"   : [
    "Assets/test/cube.mat"
],
"dependencies" : [
    "test-topbottom_png"
]
},
{
"srcFile" : "test-cube_prefab",
"targetFile" : "64c1d789c3cd334209c43996ddd509c7",
"size"       : 145581,
"version"    : 1,
"beDependent" : false,
"crc"         : 2213889952,
"resources"   : [
    "Assets/test/cube.prefab"
],
"dependencies" : [
    "test-cube_mat",
    "test-topbottom_png"
]
},
{
"srcFile" : "test-cube2_prefab",
"targetFile" : "b8fde4725f5a8f3b760678103e40ab50",
"size"       : 5705,
"version"    : 1,
"beDependent" : false,
"crc"         : 3394978099,
"resources"   : [
    "Assets/test/cube2.prefab"
],
"dependencies" : [
    "test-cube_mat",
    "test-topbottom_png"
]
},
{
"srcFile" : "test-topbottom_png",
"targetFile" : "8d4b26c395d6936e9cd6e34d9ef41511",
"size"       : 2800642,
"version"    : 1,
"beDependent" : true,
"crc"         : 255680840,
"resources"   : [
    "Assets/test/topbottom.png"
]
},
]